{
	"id": "6dbc0a26-e2c3-4664-9eb6-511bdbb7184b",
	"name": "Supernatural",
	"values": [
		{
			"key": "FirstName",
			"value": "",
			"type": "any",
			"enabled": true
		},
		{
			"key": "LastName",
			"value": "",
			"type": "any",
			"enabled": true
		},
		{
			"key": "FullName",
			"value": "",
			"type": "any",
			"enabled": true
		},
		{
			"key": "ProviderMail",
			"value": "",
			"type": "any",
			"enabled": true
		},
		{
			"key": "Mail",
			"value": "",
			"type": "any",
			"enabled": true
		},
		{
			"key": "AccessProfile",
			"value": "",
			"type": "any",
			"enabled": true
		},
		{
			"key": "count_user",
			"value": "",
			"type": "any",
			"enabled": true
		},
		{
			"key": "Random11Digits",
			"value": "",
			"type": "any",
			"enabled": true
		},
		{
			"key": "id_user",
			"value": "",
			"type": "any",
			"enabled": true
		},
		{
			"key": "msg_id_inex",
			"value": "",
			"type": "default",
			"enabled": true
		},
		{
			"key": "board_Id",
			"value": "",
			"type": "any",
			"enabled": true
		},
		{
			"key": "costCenter_id",
			"value": "",
			"type": "any",
			"enabled": true
		},
		{
			"key": "department_id",
			"value": "",
			"type": "any",
			"enabled": true
		},
		{
			"key": "board_Name",
			"value": "",
			"type": "any",
			"enabled": true
		},
		{
			"key": "costCenter_name",
			"value": "",
			"type": "any",
			"enabled": true
		},
		{
			"key": "department_name",
			"value": "",
			"type": "any",
			"enabled": true
		},
		{
			"key": "department_namePut",
			"value": "",
			"type": "any",
			"enabled": true
		}
	],
	"_postman_variable_scope": "environment",
	"_postman_exported_at": "2024-05-11T00:46:42.997Z",
	"_postman_exported_using": "Postman/11.0.11"
}